README.md
setup.py
datomize.egg-info/PKG-INFO
datomize.egg-info/SOURCES.txt
datomize.egg-info/dependency_links.txt
datomize.egg-info/requires.txt
datomize.egg-info/top_level.txt
datomizer/__init__.py
datomizer/datoenhancer.py
datomizer/datogenerator.py
datomizer/datomapper.py
datomizer/datomizer.py
datomizer/datotrainer.py
datomizer/datotuner.py
datomizer/helpers/common_helper.py
datomizer/helpers/authentication/authentication_helper.py
datomizer/helpers/autodiscovery/autodiscovery_helper.py
datomizer/helpers/business_unit_project/business_unit_project_helper.py
datomizer/helpers/datasource/datasource_helper.py
datomizer/helpers/estimation/estimation_helper.py
datomizer/helpers/generator/generator_helper.py
datomizer/helpers/train/datatuner_helper.py
datomizer/helpers/train/enhance_ml_helper.py
datomizer/helpers/train/train_helper.py
datomizer/helpers/wrapper/dt_rule_set_wrapper.py
datomizer/helpers/wrapper/evaluation_wrapper.py
datomizer/helpers/wrapper/schema_wrapper.py
datomizer/protos/autodiscoveryservice_pb2.py
datomizer/protos/constantsservice_pb2.py
datomizer/protos/datakubeservice_pb2.py
datomizer/protos/datasourceconfigservice_pb2.py
datomizer/protos/datatunerservice_pb2.py
datomizer/protos/enhancemlresults_pb2.py
datomizer/protos/fieldsettingsservice_pb2.py
datomizer/protos/infrastructuresettings_pb2.py
datomizer/protos/privacyevaluationservice_pb2.py
datomizer/protos/synthschemavalidationresult_pb2.py
datomizer/utils/constants.py
datomizer/utils/enhance_ml.py
datomizer/utils/exceptions.py
datomizer/utils/general.py
datomizer/utils/interfaces.py
datomizer/utils/messages.py
datomizer/utils/schema.py
datomizer/utils/step_types.py
datomizer/utils/thresholds.py