Metadata-Version: 2.1
Name: datomize
Version: 2.3.20
Summary: Datomize python client
Home-page: https://datomize.github.io/datomizeSDK
Author: Datomize Ltd.
Author-email: support@datomize.com
License: Apache Software License (https://www.apache.org/licenses/LICENSE-2.0)
Project-URL: Documentation, https://datomize.github.io/datomizeSDK
Keywords: machine learning
Platform: UNKNOWN
Classifier: Development Status :: 3 - Alpha
Classifier: License :: OSI Approved :: Apache Software License
Classifier: Programming Language :: Python :: 3
Classifier: Programming Language :: Python :: 3.7
Classifier: Programming Language :: Python :: 3.8
Classifier: Programming Language :: Python :: 3.9
Requires-Python: >=3.6
